playlistjockey/__init__.py
playlistjockey/filters.py
playlistjockey/main.py
playlistjockey/mixes.py
playlistjockey/selects.py
playlistjockey/utils.py
playlistjockey/spotify/__init__.py
playlistjockey/spotify/connect.py
playlistjockey/spotify/extract.py
playlistjockey/tidal/__init__.py
playlistjockey/tidal/connect.py
playlistjockey/tidal/extract.py
playlistjockey-1.0.0.dist-info/LICENSE
playlistjockey-1.0.0.dist-info/METADATA
playlistjockey-1.0.0.dist-info/WHEEL
playlistjockey-1.0.0.dist-info/top_level.txt
playlistjockey-1.0.0.dist-info/RECORD
