Metadata-Version: 2.1
Name: playlistjockey
Version: 1.0.0
Summary: Unlock innovative ways to experience playlists.
Home-page: https://robalberse.github.io/playlistjockey/
Author: Robby Alberse
Author-email: robalberse@gmail.com
License: GPL
Project-URL: Source, https://github.com/robalberse/playlistjockey
Classifier: Programming Language :: Python :: 3
Classifier: Operating System :: OS Independent
License-File: LICENSE
Requires-Dist: pandas
Requires-Dist: scikit-learn
Requires-Dist: spotipy
Requires-Dist: tidalapi
